worldbankdatatransform.py
worldbankdatatransform-0.0.2.dist-info/LICENSE.txt
worldbankdatatransform-0.0.2.dist-info/METADATA
worldbankdatatransform-0.0.2.dist-info/WHEEL
worldbankdatatransform-0.0.2.dist-info/top_level.txt
worldbankdatatransform-0.0.2.dist-info/RECORD
