Metadata-Version: 2.1
Name: worldbankdatatransform
Version: 0.0.2
Summary: Transform data.worldbank.org/indicator csv files into one variable panel data, multivariable time series data, multivariable cross section data, or multivariable panel data.
Home-page: https://github.com/fitrah9ramadhan/world-bank-data-query-tool
Author: Muhammad Nur Fitrah Ramadhan
Author-email: fitrah9ramadhan@gmail.com
License: UNKNOWN
Platform: UNKNOWN
License-File: LICENSE.txt
Requires-Dist: pandas
